LICENSE
README.md
setup.py
fda.egg-info/PKG-INFO
fda.egg-info/SOURCES.txt
fda.egg-info/dependency_links.txt
fda.egg-info/requires.txt
fda.egg-info/top_level.txt
src/__init__.py
src/fda.py
src/run.py